conversation_search/__init__.py
conversation_search/cli.py
conversation_search/core/__init__.py
conversation_search/core/date_utils.py
conversation_search/core/indexer.py
conversation_search/core/search.py
conversation_search/core/summarization.py
conversation_search/data/__init__.py
conversation_search/data/schema.sql
cc_conversation_search-0.5.3.dist-info/METADATA
cc_conversation_search-0.5.3.dist-info/WHEEL
cc_conversation_search-0.5.3.dist-info/entry_points.txt
cc_conversation_search-0.5.3.dist-info/licenses/LICENSE.txt
cc_conversation_search-0.5.3.dist-info/RECORD
