Metadata-Version: 2.4
Name: cc-conversation-search
Version: 0.5.3
Summary: Find and resume Claude Code conversations using smart hybrid extraction and JIT indexing
Project-URL: Homepage, https://github.com/akatz-ai/cc-conversation-search
Project-URL: Issues, https://github.com/akatz-ai/cc-conversation-search/issues
Author-email: akatz-ai <katzfeyalex+akatzgh@gmail.com>
License-File: LICENSE.txt
Classifier: Development Status :: 4 - Beta
Classifier: Intended Audience :: Developers
Classifier: License :: OSI Approved :: MIT License
Classifier: Programming Language :: Python :: 3
Classifier: Programming Language :: Python :: 3.9
Classifier: Programming Language :: Python :: 3.10
Classifier: Programming Language :: Python :: 3.11
Classifier: Programming Language :: Python :: 3.12
Requires-Python: >=3.9
